{
  "c_studio": [
    "Female Fake Taxi",
    null
  ],
  "comments": [
    "https://www.iafd.com/title.rme/title=finger%2dfucking+a+fit+babe/year=2016/finger%2dfucking_a_fit_babe.htm"
  ],
  "performers": {
    "remove": [],
    "append": [
      {
        "id": "4d5dea1f-9f97-4545-b6b5-1c677d4294e3",
        "name": "Rebecca More",
        "appearance": null
      },
      {
        "id": "5ac90576-a207-4be5-9ba9-ad09c8951594",
        "name": "Sienna Day",
        "appearance": null
      }
    ]
  }
}