{
  "split": {
    "name": "Victoria Tiffani",
    "shards": [
      {
        "id": "dd75e5b7-c8e3-4b6e-bf5b-0df024f2205c",
        "name": "Victoria Tiffani",
        "links": [
          "https://www.iafd.com/person.rme/perfid=tiffany_rus_10/gender=f/victoria-tiffani.htm",
          "https://www.indexxx.com/m/victoria-tiffani"
        ]
      },
      {
        "id": null,
        "name": "Ioana (Sapphic Erotica)",
        "text": "2 scenes",
        "links": [
          "https://www.indexxx.com/m/ioana-1",
          "https://stashdb.org/scenes/857bb4b6-8e1b-46d1-b101-d3d23142e31a",
          "https://stashdb.org/scenes/17eac9ce-5085-4a42-9c0c-673b5887bb07"
        ]
      }
    ],
    "notes": [
      "Mix of multiple performers named Ioana (complete list as of 2022-09-06). ",
      "Ioana was merged into Victoria Tiffani, being non unique."
    ],
    "links": [
      "https://stashdb.org/edits/b03307c7-8f78-444d-a808-af64594ee5bc",
      "https://stashdb.org/edits/5134d064-ac88-41fb-acdd-4f8248b2aebd"
    ]
  }
}
