{
  "split": {
    "name": "Cleo",
    "shards": [
      {
        "id": null,
        "name": "Cleo (TheLifeErotic)",
        "links": [
          "https://www.indexxx.com/m/cleo-2"
        ]
      },
      {
        "id": "d1e00261-e0ea-4ee4-a270-9d68a1092043",
        "name": "Adrienne Klass",
        "notes": [
          "- 1By-Day",
          "- Hot Legs and Feet"
        ],
        "links": [
          "https://www.indexxx.com/m/adrienne-klass"
        ]
      },
      {
        "id": null,
        "name": "Cleo (She's New)",
        "links": [
          "https://www.indexxx.com/m/cleo-9"
        ]
      },
      {
        "id": null,
        "name": "Messy Cleo",
        "text": "Scoreland",
        "links": [
          "https://www.indexxx.com/m/messy-cleo"
        ]
      },
      {
        "id": null,
        "name": "Cleo (2006, Russian)",
        "links": [
          "https://www.iafd.com/person.rme/perfid=cleo_eu_06/gender=f/cleo.htm",
          "https://stashdb.org/scenes/531fa894-9238-4f57-85c5-2520b887baeb"
        ]
      }
    ],
    "notes": [
      "Mix of multiple performers (partial list)"
    ]
  }
}