{
  "c_studio": [
    "GF Revenge",
    null
  ],
  "comments": [
    "https://www.iafd.com/title.rme/title=gf+revenge+10/year=2014/gf-revenge-10.htm",
    "https://www.adultdvdmarketplace.com/images/ivd_large_back_image/280556.jpg"
  ],
  "performers": {
    "remove": [
      {
        "id": "7e1d9cdb-31c5-4fcc-b1ea-3a94ff7d9bbb",
        "name": "Jade",
        "appearance": null
      }
    ],
    "append": [
      {
        "id": "14956b3e-1df8-4297-8dae-de1d53dfe666",
        "name": "Jade Dunn",
        "appearance": "Jade"
      }
    ]
  }
}