{
  "split": {
    "name": "Ruby",
    "shards": [
      {
        "id": "b571a73a-9770-4dee-a746-33f1822cee86",
        "name": "Ruby Jewel",
        "text": "(Wicked, maybe more)",
        "links": [
          "https://www.iafd.com/person.rme/perfid=ruby/gender=f/ruby.htm",
          "https://www.indexxx.com/m/ruby-jewel",
          "https://www.boobpedia.com/boobs/Ruby_Jewel",
          "https://www.freeones.com/ruby-jewel"
        ]
      }
    ],
    "notes": [
      "Mix of multiple performers (partial list)"
    ]
  }
}