{
  "split": {
    "name": "Doris",
    "shards": [
      {
        "id": "c90113c6-8337-4f1b-b29b-80001aeef36e",
        "name": "Miranda May",
        "notes": [
          "- X-Sensual",
          "- 18videoz"
        ],
        "links": [
          "https://www.iafd.com/person.rme/perfid=helenadickens/gender=f/helena-dickens.htm",
          "https://www.indexxx.com/m/miranda-may"
        ]
      },
      {
        "id": null,
        "name": "Bonny (RU)",
        "text": "TeenCoreClub",
        "links": [
          "https://www.indexxx.com/m/bonny-4",
          "https://www.iafd.com/person.rme/perfid=bonny_06/gender=f/bonny.htm"
        ]
      }
    ],
    "notes": [
      "Mix of multiple performers (partial list)"
    ]
  }
}