{
  "split": {
    "name": "Timothy",
    "shards": [
      {
        "id": null,
        "name": "Timothy (2007, Sean Cody)",
        "links": [
          "https://gayeroticvideoindex.com/performer/95785"
        ]
      },
      {
        "id": null,
        "name": "Timothy (2011, Sean Cody)",
        "links": [
          "https://gayeroticvideoindex.com/performer/95782"
        ]
      },
      {
        "id": null,
        "name": "Zane ?",
        "text": "Teeny Lovers (same tattoos, ear piercing)",
        "links": [
          "https://www.iafd.com/person.rme/perfid=um779618/gender=m/zane.htm"
        ]
      }
    ],
    "notes": [
      "Mix of multiple performers (partial list)"
    ]
  }
}