{
  "comments": [
    "https://www.iafd.com/title.rme/title=lick+my+pussy+now/year=2013/lick_my_pussy_now.htm"
  ],
  "performers": {
    "remove": [
      {
        "id": "da33326f-8ec4-4b4a-b88d-63517b4378d5",
        "name": "Elle",
        "appearance": null
      },
      {
        "id": "29bec398-5a54-4896-a1b9-c51137b52a07",
        "name": "Sophia",
        "appearance": null
      }
    ],
    "append": [
      {
        "id": "8854e677-ef09-44ac-9cbc-358eeeae397b",
        "name": "Elle Alexandra",
        "appearance": "Elle"
      },
      {
        "id": "b39c15c7-49fe-475c-8e34-d7367445c833",
        "name": "Sophia Jade",
        "appearance": "Sophia"
      }
    ]
  }
}