{
  "comments": [
    "https://www.iafd.com/title.rme/title=whatever+it+takes/year=2005/whatever-it-takes.htm"
  ],
  "performers": {
    "remove": [
      {
        "id": "d9f4c652-4387-4444-8d0e-7b116b07d4a3",
        "name": "Savannah",
        "appearance": null
      }
    ],
    "append": [
      {
        "id": null,
        "name": "Savannah",
        "appearance": null,
        "disambiguation": "2005, Reality Kings",
        "status": "new",
        "status_url": "https://www.iafd.com/person.rme/perfid=savannah_rk_05/gender=f/savannah.htm"
      }
    ]
  }
}