{
  "c_studio": [
    "Net Video Girls",
    null
  ],
  "comments": [
    "https://www.iafd.com/title.rme/title=netvideogirls%3a+cindy/year=2016/netvideogirls%3a_cindy.htm",
    "https://www.freeones.com/forums/threads/performer-guide-netvideogirls-com.101884/post-9489824",
    "Ep 2016-06-06 - Cindy ... Sabrina Rey"
  ],
  "date": "2016-06-06",
  "details": "The door opens and Cindy just stares...hahah! She was a bit surprised by the cameras rolling in her face right off the bat, and it seems to have scrambled her brains just a little bit...she recovers though and tries to play it off but she's immediately put on the defensive which is just where the Maestro wants her to be! He plays these girls like a fiddle here on Net Video Girls, talking them to the hotel saying they would be auditioning for a calendar girl, but they end up just getting naked and fucked on camera because there IS no actual calendar. Cindy here is gorgeous, she's an 18 year old amateur stunner with great legs and beautiful eyes, and it doesnt take long before she's stripping down and then sucking cock, getting her tight teen pussy fucked, and taking a load of cum in the mouth!",
  "performers": {
    "remove": [
      {
        "id": "8f46e361-22d3-493b-999d-173923c772e9",
        "name": "Cindy",
        "appearance": null
      }
    ],
    "append": [
      {
        "id": "0f685bc9-1b61-4266-a605-e9385c333e45",
        "name": "Sabrina Rey",
        "appearance": "Cindy"
      }
    ]
  }
}