{
  "split": {
    "name": "Holly",
    "shards": [
      {
        "id": null,
        "name": "Holly (ALS Scan)",
        "links": [
          "https://www.indexxx.com/m/holly-18"
        ]
      },
      {
        "id": null,
        "name": "Holly (Nubiles)",
        "links": [
          "https://www.indexxx.com/m/holly-1"
        ]
      },
      {
        "id": "e19af39a-0438-4cf0-89b2-0b54b9cbc61c",
        "name": "Hollie Stevens",
        "notes": [
          "- Teen Teacher \"Blonde applies her fuck skills\": same as \"Detention Whores 5\" Scene 4"
        ],
        "links": [
          "https://www.iafd.com/person.rme/perfid=hollystevens/gender=f/hollie-stevens.htm",
          "https://www.indexxx.com/m/hollie-stevens"
        ]
      },
      {
        "id": "fb50ddbe-e8d5-4189-8ceb-b621c9cf3a19",
        "name": "Holly Wellin",
        "notes": [
          "- Teen Teacher \"Teach assfucks blonde in class\": same as \"Teacher's Pet 12\" Scene 2"
        ],
        "links": [
          "https://www.iafd.com/person.rme/perfid=hollywellin/gender=f/holly-wellin.htm",
          "https://www.indexxx.com/m/holly-wellin"
        ]
      }
    ],
    "notes": [
      "Mix of multiple performers (partial list)"
    ]
  }
}