{
  "name": "Michelle Wild (HU)",
  "split": {
    "name": "Michelle Wild",
    "shards": [
      {
        "id": null,
        "name": "Michelle Wild (HU)",
        "notes": [
          "- Michelle Wild D @ Rocco Siffredi",
          "- Michelle Wild D @ Fame Digital (Network)",
          "- Christoph Clark Online",
          "- DDF Network",
          "- Perfect Gonzo",
          "- Twistys"
        ],
        "links": [
          "https://www.iafd.com/person.rme/perfid=michellewild/gender=f/michelle-wild.htm",
          "https://www.indexxx.com/m/michelle-wild"
        ]
      },
      {
        "id": null,
        "name": "Michelle Wild (CZ)",
        "notes": [
          "- Anal Acrobats: same as Rim My Gape 2 Scene 3",
          "- Devil's Gangbangs",
          "- Doghouse Digital",
          "- Rocco Siffredi \"Dirty Dreams #05\""
        ],
        "links": [
          "https://www.iafd.com/person.rme/perfid=michellewild2/gender=f/michelle-wild.htm",
          "https://www.indexxx.com/m/mischelle"
        ]
      }
    ],
    "notes": [
      "Mix of multiple performers (complete list as of 2022-07-25)"
    ]
  },
  "urls": [
    "https://www.iafd.com/person.rme/perfid=michellewild/gender=f/michelle-wild.htm",
    "https://www.indexxx.com/m/michelle-wild"
  ]
}