{
  "split": {
    "name": "Nancy",
    "shards": [
      {
        "id": "797e8f2b-6872-482f-878e-a656481d6dc4",
        "name": "Nancy Bell",
        "text": "(Nubiles)",
        "links": [
          "https://www.iafd.com/person.rme/perfid=nancybell/gender=f/nancy-bell.htm",
          "https://www.indexxx.com/m/nancy-bell"
        ]
      },
      {
        "id": null,
        "name": "Nancy (2009, Net Video Girls)"
      },
      {
        "id": null,
        "name": "Nancy (Sapphic Erotica)",
        "links": [
          "https://www.iafd.com/person.rme/perfid=nansy_hun_08/gender=f/nansy.htm",
          "https://www.indexxx.com/m/nansy-1"
        ]
      }
    ],
    "notes": [
      "Mix of multiple performers (partial list)"
    ]
  }
}