{
  "c_studio": [
    "Facial Fest",
    null
  ],
  "comments": [
    "https://www.iafd.com/title.rme/title=tips+from+a+pornstar+rachel+starr/year=2012/tips-from-a-pornstar-rachel-starr.htm"
  ],
  "performers": {
    "remove": [
      {
        "id": "d4092195-4585-4c6f-bf24-4b40a2e1b175",
        "name": "Amber",
        "appearance": null
      }
    ],
    "append": [
      {
        "id": null,
        "name": "Amber Rosexoxo",
        "appearance": "Amber",
        "status": "c",
        "status_url": "https://stashdb.org/edits/2e143dfd-115b-4ed7-b8b1-5c1e7ee40df1"
      },
      {
        "id": "816ea58e-7ae6-41aa-84af-f3b40b5595e2",
        "name": "Preston Parker",
        "appearance": null
      }
    ]
  }
}