{
  "split": {
    "name": "Veronica",
    "shards": [
      {
        "id": null,
        "name": "Veronica Jones",
        "text": "Nubiles circa 2006",
        "links": [
          "https://www.indexxx.com/m/veronica-jones-1",
          "https://www.thenude.com/_7215.htm"
        ]
      },
      {
        "id": null,
        "name": "Veronica Green",
        "text": "Net Video Girls (2016)",
        "links": [
          "https://www.iafd.com/person.rme/perfid=veronicagreen/gender=f/veronica-green.htm",
          "https://www.indexxx.com/m/veronica-green",
          "https://www.freeones.com/forums/threads/veronica-green.896126/"
        ]
      }
    ],
    "notes": [
      "Mix of multiple performers (partial list)"
    ]
  }
}