{
  "c_studio": [
    "18 Years Old",
    null
  ],
  "performers": {
    "remove": [
      {
        "id": "06dab1fb-811c-4a90-b061-97beac4b56b2",
        "name": "Jynx & Heather",
        "appearance": null
      }
    ],
    "append": [
      {
        "id": "0e41ebc2-e5a4-4f9b-b6f0-bf0b50c2a1cb",
        "name": "Jynx Maze",
        "appearance": "Jynx"
      },
      {
        "id": "d26adc3e-65be-4734-ac2d-04d971e4f7d7",
        "name": "Heather Starlet",
        "appearance": "Heather"
      },
      {
        "id": "7d564c9b-93ff-49f5-aceb-607b878e0057",
        "name": "Bruce Venture",
        "appearance": null
      }
    ]
  }
}