{
  "split": {
    "name": "Camden",
    "shards": [
      {
        "id": null,
        "name": "Nata Nice",
        "text": "The Life Erotic",
        "links": [
          "https://www.iafd.com/person.rme/perfid=natanice/gender=f/nata-nice.htm"
        ]
      },
      {
        "id": null,
        "name": "Camden (Sean Cody 2015)",
        "links": [
          "https://gayeroticvideoindex.com/performer/102144"
        ]
      }
    ],
    "notes": [
      "Mix of multiple performers (complete list as of 2022-08-21)"
    ]
  }
}
