{
  "split": {
    "name": "Caleb",
    "shards": [
      {
        "id": "564e2c59-10d6-4e67-821d-37107174a962",
        "name": "Caleb (Sean Cody 2006)",
        "links": [
          "https://gayeroticvideoindex.com/performer/90145"
        ]
      },
      {
        "id": "915f783e-8016-4504-ab5a-65f29cf511ec",
        "name": "Caleb (Sean Cody 2012)",
        "links": [
          "https://gayeroticvideoindex.com/performer/103430"
        ]
      },
      {
        "id": "508a5ad5-e45a-4606-ba20-f1dbce56288c",
        "name": "Caleb (Sean Cody 2016)",
        "links": [
          "https://gayeroticvideoindex.com/performer/106284",
          "https://www.iafd.com/person.rme/perfid=caleb_seancody/gender=m/caleb.htm"
        ]
      }
    ],
    "notes": [
      "Mix of multiple performers (complete list as of 2022-11-5)"
    ]
  }
}
