{
  "c_studio": [
    "Peter North",
    null
  ],
  "performers": {
    "remove": [
      {
        "id": "57a55562-8d05-4ad9-aaaa-c811647946fa",
        "name": "Kendall",
        "appearance": null
      }
    ],
    "append": [
      {
        "id": "07164df2-3629-470d-b028-d93554676ada",
        "name": "Alison Faye",
        "appearance": "Kendall"
      },
      {
        "id": "a94908b3-8f69-4278-8910-5157076e77c8",
        "name": "Peter North",
        "appearance": null
      }
    ]
  }
}