{
  "c_studio": [
    "Cum Fiesta",
    null
  ],
  "comments": [
    "https://www.iafd.com/title.rme/title=double+trouble+%28iv%29/year=2007/double-trouble-%28iv%29.htm"
  ],
  "performers": {
    "remove": [
      {
        "id": "415368f0-98d3-48f0-a290-65a7d283afa2",
        "name": "Mike",
        "appearance": null
      }
    ],
    "append": [
      {
        "id": "a311ff77-1978-445d-a79f-0279d7c0bfe1",
        "name": "Mike Adriano",
        "appearance": "Mike"
      },
      {
        "id": "220b28d5-529c-4b98-b8f6-f3cf20116d96",
        "name": "Riley Evans",
        "appearance": null
      }
    ]
  }
}