{
  "split": {
    "name": "Ellie",
    "shards": [
      {
        "id": "3a23bd94-9548-4aab-87c0-e09c5fda6322",
        "name": "Ellie Ray",
        "links": [
          "https://www.iafd.com/person.rme/perfid=elliy_19/gender=f/ellie-ray.htm",
          "https://www.indexxx.com/m/ellie-ray"
        ]
      },
      {
        "id": null,
        "name": "Ellie (Backroom Casting Couch 2017)",
        "links": [
          "https://www.backroomcastingcouch.com/models/Ellie-2.html",
          "https://stashdb.org/scenes/41dc8801-d82f-415e-ad39-a10bf5281e61"
        ]
      },
      {
        "id": null,
        "name": "Ellie (Backroom Casting Couch 2012)",
        "links": [
          "https://www.backroomcastingcouch.com/models/Ellie.html",
          "https://stashdb.org/scenes/4710687e-5585-4a8f-9839-a2e267ff47b1"
        ]
      },
      {
        "id": null,
        "name": "Ellie (NVG 2015)",
        "links": [
          "https://calendarauditions.com/play/15_ellieCC/",
          "https://netvideogirls.net/blonde-ellie-twerks-and-slammed-at-video-casting/"
        ]
      }
    ],
    "notes": [
      "Mix of multiple performers (complete list as of 2022-06-06) ",
      "See edit: https://stashdb.org/edits/4b64b07e-8126-48a7-9c27-518f23b9020c"
    ]
  }
}