{
  "split": {
    "name": "Tristan",
    "shards": [
      {
        "id": "7416cd3b-248d-4083-b673-2852e6840dfd",
        "name": "Tristan Kingsley"
      },
      {
        "id": "eb3c9403-a86d-4ca6-bbe2-2cfb15073f80",
        "name": "Tristan Berrimore"
      },
      {
        "id": "a5f7aeac-8940-4dd4-9216-35fa63a911b2",
        "name": "Tristan Segal"
      },
      {
        "id": null,
        "name": "8 Unidentified scenes"
      }
    ],
    "notes": [
      "Mixed men and women",
      "@peolic: 9/17 scenes added to Scene-Performers"
    ]
  }
}