{
  "comments": [
    "https://www.freeones.com/forums/threads/performer-guide-netvideogirls-com.101884/post-9489821",
    "Ep 2015-03-04 - Isla (with Madison and Lane) ... Rebel Lynn"
  ],
  "date": "2015-03-04",
  "performers": {
    "remove": [
      {
        "id": "bf8cb166-c968-4963-9dc8-a78ca351e090",
        "name": "Lane",
        "appearance": null
      },
      {
        "id": "00f00023-9b0b-45f7-ac2a-14f39e3c9959",
        "name": "Madison",
        "appearance": null
      }
    ],
    "append": [
      {
        "id": "5bfb1e43-7b37-42cf-8ba7-3ad2acee306a",
        "name": "Audrey Holiday",
        "appearance": "Lane"
      },
      {
        "id": "2119d693-738b-43fe-87f7-2e2b91b2b96f",
        "name": "Blair Summers",
        "appearance": "Madison"
      }
    ]
  }
}