{
  "split": {
    "name": "Krystal",
    "shards": [
      {
        "id": null,
        "name": "Krystal (2004 Reality Kings)",
        "links": [
          "https://www.iafd.com/person.rme/perfid=krystal_rk_04/gender=f/krystal.htm",
          "https://www.indexxx.com/m/krystal-2"
        ]
      },
      {
        "id": null,
        "name": "Krystal Jewels",
        "text": "(8th Street Latinas)",
        "links": [
          "https://www.iafd.com/person.rme/perfid=krystal_bd/gender=f/krystal-jewels.htm",
          "https://www.indexxx.com/m/krystal-10"
        ]
      },
      {
        "id": null,
        "name": "Krystal (2013 BRCC)"
      },
      {
        "id": null,
        "name": "Krystal (2008, Fantasy Massage)",
        "links": [
          "https://www.iafd.com/person.rme/perfid=krystal_fama/gender=f/krystal.htm"
        ]
      },
      {
        "id": null,
        "name": "Krystal (2005, MILF Next Door)",
        "links": [
          "https://www.iafd.com/person.rme/perfid=krystal_rk_05/gender=f/krystal.htm",
          "https://www.indexxx.com/m/krystal-1"
        ]
      },
      {
        "id": null,
        "name": "Crystal Kerrington (2002-2005)",
        "text": "(Give Me Teens)",
        "links": [
          "https://www.iafd.com/person.rme/perfid=ckerrington/gender=f/crystal-kerrington.htm",
          "https://www.iafd.com/title.rme/title=teen+tryouts+audition+20/year=2002/teen-tryouts-audition-20.htm"
        ]
      }
    ],
    "notes": [
      "Mix of multiple performers (complete list)"
    ]
  }
}