{
  "comments": [
    "https://www.iafd.com/title.rme/title=backroom+casting+couch+1024%3a+audrey/year=2008/backroom_casting_couch_1024%3a_audrey.htm"
  ],
  "performers": {
    "remove": [
      {
        "id": "5c833b69-3bf2-4a73-b4e4-1f214f3ed20a",
        "name": "Audrey",
        "appearance": null
      }
    ],
    "append": [
      {
        "id": null,
        "name": "Madison Keyz",
        "appearance": "Audrey",
        "status": "new",
        "status_url": "https://www.iafd.com/person.rme/perfid=madison_povtrain/gender=f/madison-keyz.htm"
      }
    ]
  }
}