{
  "c_studio": [
    "Stunning 18",
    null
  ],
  "comments": [
    "https://www.indexxx.com/set/989433/stunning-18-angelica/"
  ],
  "performers": {
    "remove": [
      {
        "id": "53343ddc-5fe9-4d25-bf88-fe050436de1d",
        "name": "Angelica",
        "appearance": null
      }
    ],
    "append": [
      {
        "id": null,
        "name": "Angelina Ash",
        "appearance": "Angelica",
        "disambiguation": "2019-",
        "status": "new",
        "status_url": "https://www.indexxx.com/m/angelina-ash",
        "notes": [
          "https://www.thenude.com/Angelina%20Ash_46398.htm"
        ]
      }
    ]
  }
}