{
  "c_studio": [
    "Naughty Mag",
    null
  ],
  "comments": [
    "https://www.iafd.com/title.rme/title=open%2dminded+cutie/year=2020/open%2dminded-cutie.htm"
  ],
  "performers": {
    "remove": [
      {
        "id": "9a24a081-2352-4c4e-a209-ef7ce1619b79",
        "name": "Jordan Jay",
        "appearance": null
      }
    ],
    "append": [
      {
        "id": null,
        "name": "Jordan Jay",
        "appearance": null,
        "disambiguation": "2020",
        "status": "new",
        "status_url": "https://www.iafd.com/person.rme/perfid=jordanjay_19/gender=f/jordan-jay.htm",
        "notes": [
          "https://www.indexxx.com/m/jordan-jay",
          "https://www.thenude.com/Jordan%20Jay_50425.htm"
        ]
      }
    ]
  }
}